mobile_ua/UA.pkl
mobile_ua/useragent.py
mobile_ua-1.0.3.dist-info/METADATA
mobile_ua-1.0.3.dist-info/WHEEL
mobile_ua-1.0.3.dist-info/top_level.txt
mobile_ua-1.0.3.dist-info/RECORD
