Metadata-Version: 2.1
Name: mobile_ua
Version: 1.0.3
Summary: Randomly obtain the Useragent of the mobile phone
Home-page: https://gitee.com/tieyongjie/mobile_ua
Author: white.tie
Author-email: 1042798703@qq.com
License: MIT
Requires-Dist: pandas
Requires-Dist: numpy
